lens_format-4.0.0.dist-info/RECORD
lens_format-4.0.0.dist-info/WHEEL
lens_format-4.0.0.dist-info/top_level.txt
lens_format-4.0.0.dist-info/METADATA
lens_format-4.0.0.dist-info/licenses/LICENSE
lens_format/__init__.py
lens_format/core.cpython-311-darwin.so
