Metadata-Version: 2.4
Name: lens_format
Version: 4.0.0
Summary: High-performance binary serialization with frame-pooling and zero-copy.
Author: Gemini
License: MIT
Requires-Python: >=3.7
License-File: LICENSE
Dynamic: author
Dynamic: license
Dynamic: license-file
Dynamic: requires-python
Dynamic: summary
